urbackup/__init__.py
python_urbackup-0.1.2.dist-info/LICENSE
python_urbackup-0.1.2.dist-info/METADATA
python_urbackup-0.1.2.dist-info/WHEEL
python_urbackup-0.1.2.dist-info/top_level.txt
python_urbackup-0.1.2.dist-info/RECORD
