Metadata-Version: 2.1
Name: python-urbackup
Version: 0.1.2
Summary: Python wrapper to access and control an UrBackup server
Home-page: https://github.com/judahpaul16/python-urbackup
Author: Judah Paul
Author-email: me@judahpaul.com
License: Apache License 2.0
Keywords: urbackup web api client
Platform: UNKNOWN
Classifier: Development Status :: 3 - Alpha
Classifier: Intended Audience :: Developers
Classifier: License :: OSI Approved :: Apache Software License
Classifier: Programming Language :: Python :: 3.8
Classifier: Programming Language :: Python :: 3.9
Classifier: Programming Language :: Python :: 3.10
Classifier: Programming Language :: Python :: 3.11
Classifier: Programming Language :: Python :: 3.12
License-File: LICENSE
Requires-Dist: requests
Requires-Dist: urllib3
Provides-Extra: dev
Provides-Extra: test
